[
  {
    "name": "ENERGOLUX SAS",
    "desc": "Настенная инверторная сплит-система с классом энергоэффективности A+++, Wi-Fi управлением и ночной режимом.",
    "image": "https://energolux.ru.com/images/logo.png",
    "image_note": "Плейсхолдер — нужно заменить на фото модели с сайта"
  },
  {
    "name": "ENERGOLUX SAM",
    "desc": "Мульти-сплит-система — до 4 внутренних блоков на один наружный блок.",
    "image": "https://energolux.ru.com/images/logo.png",
    "image_note": "Плейсхолдер — нужно заменить на фото модели с сайта"
  },
  {
    "name": "ENERGOLUX SAD",
    "desc": "Канальная серия для скрытой установки за подвесным потолком. Идеальна для ремонта.",
    "image": "https://energolux.ru.com/images/logo.png",
    "image_note": "Плейсхольдер — нужно заменить на фото модели с сайта"
  }
]
